waterbear/__init__.py
waterbear/test_waterbear.py
waterbear/waterbear.py
waterbear-2.6.6.dist-info/LICENSE.md
waterbear-2.6.6.dist-info/METADATA
waterbear-2.6.6.dist-info/WHEEL
waterbear-2.6.6.dist-info/top_level.txt
waterbear-2.6.6.dist-info/RECORD
