Metadata-Version: 2.1
Name: waterbear
Version: 2.6.6
Summary: A utility that makes it easy to use dot notation with python dictionaries
Home-page: https://github.com/episodeyang/waterbear
Author: Ge Yang
Author-email: yangge1987@gmail.com
License: UNKNOWN
Keywords: waterbear,dict,dot-notation
Platform: UNKNOWN
Classifier: Development Status :: 4 - Beta
Classifier: Intended Audience :: Science/Research
Classifier: Programming Language :: Python :: 3
